LICENSE.txt
MANIFEST.in
README.md
setup.cfg
setup.py
bx/__init__.py
bx/db.py
bx.egg-info/PKG-INFO
bx.egg-info/SOURCES.txt
bx.egg-info/dependency_links.txt
bx.egg-info/requires.txt
bx.egg-info/top_level.txt