Metadata-Version: 1.1
Name: bx
Version: 0.1.0
Summary: Simple in-memory storage for Python
Home-page: https://github.com/tylucaskelley/bx-python
Author: Ty-Lucas Kelley
Author-email: tylucaskelley@gmail.com
License: MIT
Download-URL: https://github.com/tylucaskelley/bx-python/tarball/v0.1.0
Platform: UNKNOWN
Classifier: Programming Language :: Python
Classifier: Operating System :: MacOS :: MacOS X
Classifier: Operating System :: POSIX :: Linux
Classifier: License :: OSI Approved :: MIT License
Classifier: Intended Audience :: Developers
Classifier: Topic :: Database
Classifier: Topic :: Software Development :: Libraries :: Python Modules
